<?xml version="1.0" encoding="UTF-8"?>
<LanguageData>

  <!-- implants -->

	<InstallJoywire.label>РІСЃС‚Р°РЅРѕРІРёС‚Рё Р¤Р»Р°РЅРґРµСЂСЃ-С‡С–Рї</InstallJoywire.label>
	<InstallJoywire.description>Р’СЃС‚Р°РЅРѕРІРёС‚Рё Р¤Р»Р°РЅРґРµСЂСЃ-С‡С–Рї.</InstallJoywire.description>
	<InstallJoywire.jobString>Встановлює Фландерс-чіп.<</InstallJoywire.jobString>

	<InstallPainstopper.label>РІСЃС‚Р°РЅРѕРІРёС‚Рё Р°Р»РіРѕ-Р±Р»РѕРє</InstallPainstopper.label>
	<InstallPainstopper.description>Р’СЃС‚Р°РЅРѕРІРёС‚Рё Р°Р»РіРѕ-Р±Р»РѕРє.</InstallPainstopper.description>
	<InstallPainstopper.jobString>Встановлює алго-блок.<</InstallPainstopper.jobString>

</LanguageData>
