<?xml version="1.0" encoding="utf-8" ?>
<LanguageData>

  <FactionGreetingHostile>Представник {0} осипає монітор епітетами й відключається.</FactionGreetingHostile>
  <FactionGreetingWary>Представник {0} обережно вітає {1} й питає HIS у чому справа.</FactionGreetingWary>
  <FactionGreetingWarm>Представник {0} тепло вітає {1} й питає як справи в колонії.</FactionGreetingWarm>

  <Disconnect>Відключитися</Disconnect>

  <OfferGift>Запропонувати подарунок</OfferGift>
  <NeedSilverLaunchable>потрібно {0} срібла</NeedSilverLaunchable>
  <NotEnoughSilver>Срібла невистачає</NotEnoughSilver>
  <SilverForGoodwill>{0} срібла за {1} репутації</SilverForGoodwill>
  <SilverGiftSent>Представник {0} дякую вам.\n\n(Репутація покращилась на {1})</SilverGiftSent>


  <RequestMilitaryAid>Запрос негайної військової допомоги ({0} к репутації)</RequestMilitaryAid>
  <MilitaryAidConfirmMutualEnemy>{0} не допоможуть вам у війні з фракціями, що не є їх ворогами. Це поширюється на {1}, що погрожують вам. Ви все ще бажаєте викликати допомогу?</MilitaryAidConfirmMutualEnemy>
  <CallConfirm>Так, викликати їх у будь-якому випадку.</CallConfirm>
  <CallCancel>Ні, не потрібно.</CallCancel>
  <MilitaryAidSent>Представник {0} згоден відправити бійців вам на допомогу.</MilitaryAidSent>
  
  
</LanguageData>