<?xml version="1.0" encoding="UTF-8"?>
<LanguageData>
  
  <!-- EN: archotech arm -->
  <ArchotechArm.label>архотехніна рука</ArchotechArm.label>
  <!-- EN: An installed archotech arm. -->
  <ArchotechArm.description>Встановлена архотехнічна рука.</ArchotechArm.description>
  <!-- EN: fist -->
  <ArchotechArm.comps.HediffComp_VerbGiver.tools.fist.label>кулак</ArchotechArm.comps.HediffComp_VerbGiver.tools.fist.label>
  <!-- EN: an archotech arm -->
  <ArchotechArm.labelNoun>архотехнічна рука</ArchotechArm.labelNoun>
  
  <!-- EN: archotech eye -->
  <ArchotechEye.label>архотехнічне око</ArchotechEye.label>
  <!-- EN: An installed archotech eye. -->
  <ArchotechEye.description>Встановлене архотехнічне око.</ArchotechEye.description>
  <!-- EN: an archotech eye -->
  <ArchotechEye.labelNoun>архотехнічне око</ArchotechEye.labelNoun>
  
  <!-- EN: archotech leg -->
  <ArchotechLeg.label>архотехнічна нога</ArchotechLeg.label>
  <!-- EN: An installed archotech leg. -->
  <ArchotechLeg.description>Встановлена архотехнічна нога.</ArchotechLeg.description>
  <!-- EN: an archotech leg -->
  <ArchotechLeg.labelNoun>архотехнічна нога</ArchotechLeg.labelNoun>
  
</LanguageData>
