<?xml version="1.0" encoding="UTF-8"?>
<LanguageData>
  
  <!-- EN: alpaca -->
  <Alpaca.label>альпака</Alpaca.label>
  
  <!-- EN: bison -->
  <Bison.label>бізон</Bison.label>
  <!-- EN: bison calf -->
  <Bison.lifeStages.bison_calf.label>бізоненя</Bison.lifeStages.bison_calf.label>
  <!-- EN: bison calves -->
  <Bison.lifeStages.bison_calf.labelPlural>бізоненята</Bison.lifeStages.bison_calf.labelPlural>
  
  <!-- EN: chicken -->
  <Chicken.label>курка</Chicken.label>
  <!-- EN: hen -->
  <Chicken.labelFemale>квочка</Chicken.labelFemale>
  <!-- EN: rooster -->
  <Chicken.labelMale>півень</Chicken.labelMale>
  <!-- EN: chick -->
  <Chicken.lifeStages.chick.label>курча</Chicken.lifeStages.chick.label>
  <!-- EN: cockerel -->
  <Chicken.lifeStages.cockerel.labelMale>півник</Chicken.lifeStages.cockerel.labelMale>
  
  <!-- EN: cow -->
  <Cow.label>корова</Cow.label>
  <!-- EN: bull -->
  <Cow.labelMale>бик</Cow.labelMale>
  <!-- EN: calf -->
  <Cow.lifeStages.calf.label>теля</Cow.lifeStages.calf.label>
  <!-- EN: calves -->
  <Cow.lifeStages.calf.labelPlural>телята</Cow.lifeStages.calf.labelPlural>
  
  <!-- EN: donkey -->
  <Donkey.label>ослик</Donkey.label>
  <!-- EN: donkey foal -->
  <Donkey.lifeStages.donkey_foal.label>осленя</Donkey.lifeStages.donkey_foal.label>
  
  <!-- EN: duck -->
  <Duck.label>качка</Duck.label>
  <!-- EN: duckling -->
  <Duck.lifeStages.duckling.label>каченя</Duck.lifeStages.duckling.label>
  
  <!-- EN: goat -->
  <Goat.label>козел</Goat.label>
  <!-- EN: goat doe -->
  <Goat.labelFemale>коза</Goat.labelFemale>
  <!-- EN: baby goat -->
  <Goat.lifeStages.baby_goat.label>козеня</Goat.lifeStages.baby_goat.label>
  
  <!-- EN: goose -->
  <Goose.label>гусак</Goose.label>
  <!-- EN: geese -->
  <Goose.labelPlural>гуси</Goose.labelPlural>
  
  <!-- EN: guinea pig -->
  <GuineaPig.label>морська свинка</GuineaPig.label>
  
  <!-- EN: horse -->
  <Horse.label>кінь</Horse.label>
  <!-- EN: mare -->
  <Horse.labelFemale>кобила</Horse.labelFemale>
  <!-- EN: stallion -->
  <Horse.labelMale>жеребець</Horse.labelMale>
  <!-- EN: foal -->
  <Horse.lifeStages.foal.label>лоша</Horse.lifeStages.foal.label>
  
  <!-- EN: pig -->
  <Pig.label>свиня</Pig.label>
  <!-- EN: sow -->
  <Pig.labelFemale>матка</Pig.labelFemale>
  <!-- EN: piglet -->
  <Pig.lifeStages.piglet.label>порося</Pig.lifeStages.piglet.label>
  
  <!-- EN: sheep -->
  <Sheep.label>вівця</Sheep.label>
  <!-- EN: ewe -->
  <Sheep.labelFemale>вівця</Sheep.labelFemale>
  <!-- EN: ram -->
  <Sheep.labelMale>баран</Sheep.labelMale>
  <!-- EN: sheep -->
  <Sheep.labelPlural>вівці</Sheep.labelPlural>
  <!-- EN: lamb -->
  <Sheep.lifeStages.lamb.label>ягня</Sheep.lifeStages.lamb.label>
  <!-- EN: lambs -->
  <Sheep.lifeStages.lamb.labelPlural>ягнята</Sheep.lifeStages.lamb.labelPlural>
  
  <!-- EN: yak -->
  <Yak.label>як</Yak.label>
  <!-- EN: yak -->
  <Yak.labelMale>як</Yak.labelMale>
  <!-- EN: yak calf -->
  <Yak.lifeStages.yak_calf.label>теля яка</Yak.lifeStages.yak_calf.label>
  <!-- EN: yak calves -->
  <Yak.lifeStages.yak_calf.labelPlural>телята яка</Yak.lifeStages.yak_calf.labelPlural>
  
</LanguageData>
