<?xml version="1.0" encoding="utf-8"?>
<LanguageData>

  <MeleeWeapon_Mace.label>булава</MeleeWeapon_Mace.label>
  <MeleeWeapon_Mace.description>Вишукана булава, створена для ефективного розмаху та смертоносного удару.</MeleeWeapon_Mace.description>
  <MeleeWeapon_Mace.tools.0.label>руків'я</MeleeWeapon_Mace.tools.0.label>
  <MeleeWeapon_Mace.tools.1.label>навершя</MeleeWeapon_Mace.tools.1.label>

  <MeleeWeapon_Gladius.label>гладіус</MeleeWeapon_Gladius.label>
  <MeleeWeapon_Gladius.description>Короткий меч давнього дизайну. Хороший для ударів або порізів. Він легкий і спритний, що іноді дозволяє бити сильніше ніж важкою зброєю.</MeleeWeapon_Gladius.description>
  <MeleeWeapon_Gladius.tools.0.label>руків'я</MeleeWeapon_Gladius.tools.0.label>
  <MeleeWeapon_Gladius.tools.1.label>вістря</MeleeWeapon_Gladius.tools.1.label>
  <MeleeWeapon_Gladius.tools.2.label>лезо</MeleeWeapon_Gladius.tools.2.label>

  <MeleeWeapon_LongSword.label>довгий меч</MeleeWeapon_LongSword.label>
  <MeleeWeapon_LongSword.description>Довгий меч, старовинна зброя королів, використовується для колючо-рубаючих атак.</MeleeWeapon_LongSword.description>
  <MeleeWeapon_LongSword.tools.0.label>руків'я</MeleeWeapon_LongSword.tools.0.label>
  <MeleeWeapon_LongSword.tools.1.label>вістря</MeleeWeapon_LongSword.tools.1.label>
  <MeleeWeapon_LongSword.tools.2.label>лезо</MeleeWeapon_LongSword.tools.2.label>


</LanguageData>
