<?xml version="1.0" encoding="UTF-8"?>
<LanguageData>

  <!-- Frag grenade -->

	<Weapon_GrenadeFrag.label>Гранати</Weapon_GrenadeFrag.label>
	<Proj_GrenadeFrag.label>Граната</Proj_GrenadeFrag.label>
	<Weapon_GrenadeFrag.description>Старомодна осколкова граната.</Weapon_GrenadeFrag.description>
	<Weapon_GrenadeFrag.verbs.0.label>Кинути гранату</Weapon_GrenadeFrag.verbs.0.label>

  <!-- Molotov cocktail -->

	<Weapon_GrenadeMolotov.label>Коктейль Молотова</Weapon_GrenadeMolotov.label>
	<Proj_GrenadeMolotov.label>Коктейль Молотова</Proj_GrenadeMolotov.label>
	<Weapon_GrenadeMolotov.description>Скляна пляшка з легкозаймистою рідиною всередині та шматком палаючої тканини у горлечку. Улюблена зброя хуліганів та відчайдушних бійців у всіх куточках світу.</Weapon_GrenadeMolotov.description>
	<Weapon_GrenadeMolotov.verbs.0.label>Кинути коктейль Молотова</Weapon_GrenadeMolotov.verbs.0.label>

  <!-- EMP grenade -->

	<Weapon_GrenadeEMP.label>ЕМІ гранати</Weapon_GrenadeEMP.label>
	<Proj_GrenadeEMP.label>ЕМІ граната</Proj_GrenadeEMP.label>
	<Weapon_GrenadeEMP.description>Електромагнітні гранати, що завдають шкоди електроним пристроям.</Weapon_GrenadeEMP.description>
	<Weapon_GrenadeEMP.verbs.0.label>Кинути ЕМІ гранату</Weapon_GrenadeEMP.verbs.0.label>

</LanguageData>
