<?xml version="1.0" encoding="UTF-8"?>
<LanguageData>

  <!-- Melee Weapons -->

	<MeleeWeapon_Gladius.label>гладіус</MeleeWeapon_Gladius.label>
	<MeleeWeapon_Gladius.description>Античний короткий меч. Ним легко щось відрубати або когось проткнути.</MeleeWeapon_Gladius.description>

	<MeleeWeapon_LongSword.label>довгий меч</MeleeWeapon_LongSword.label>
	<MeleeWeapon_LongSword.description>Це - зброя лицарів та королів, в правильних руках він буде смертоносною колючо-рубаючою зброєю.</MeleeWeapon_LongSword.description>

	<MeleeWeapon_Knife.label>ніж</MeleeWeapon_Knife.label>
	<MeleeWeapon_Knife.description>Звичайний ніж.</MeleeWeapon_Knife.description>

	<MeleeWeapon_Shiv.label>заточка</MeleeWeapon_Shiv.label>
	<MeleeWeapon_Shiv.description>Імпровізована зброя, схожа на ніж.</MeleeWeapon_Shiv.description>

	<MeleeWeapon_Spear.label>спис</MeleeWeapon_Spear.label>
	<MeleeWeapon_Spear.description>Древко, увінчане гострим наконечником для атакування ворогів у ближньому бою.</MeleeWeapon_Spear.description>

	<MeleeWeapon_Mace.label>булава</MeleeWeapon_Mace.label>
	<MeleeWeapon_Mace.description>Вдосконалений варіант дубини, з покращеним розмахом та ударом за рахунок розкручення.</MeleeWeapon_Mace.description>

	<MeleeWeapon_Club.label>дрюк</MeleeWeapon_Club.label>
	<MeleeWeapon_Club.description>Найдавніша зброя людства - добрий шматок дерева для забивання ворогів насмерть. Примітивно, але ефективно.</MeleeWeapon_Club.description>

</LanguageData>
