<?xml version="1.0" encoding="UTF-8"?>
<LanguageData>
  
  <!-- EN: raw humanlike meat eaten -->
  <AteRawHumanlikeMeat.label>з'їдене сире м'ясо людиноподібної істоти</AteRawHumanlikeMeat.label>
  <!-- EN:
    <li>tale_noun->[PAWN_nameDef]'s eating of human meat</li>
    <li>image->[PAWN_nameFull] [eat_gerund] the meat of a fellow humanoid [circumstance_group]</li>
    <li>image->[PAWN_nameFull] [eat_gerund] meat from a humanlike arm [circumstance_group]</li>
    <li>image->[PAWN_nameFull] [eat_gerund] flesh of a humanoid [circumstance_group]</li>
    <li>eat_gerund->eating</li>
    <li>eat_gerund->ingesting</li>
    <li>eat_gerund->chewing</li>
    <li>eat_gerund->chowing down on</li>
    <li>eat_gerund->consuming</li>
    <li>eat_gerund->swallowing</li>
    <li>eat_gerund->cannibalizing</li>
    <li>circumstance_phrase->with a sense of purpose</li>
    <li>circumstance_phrase->with no hint of shame</li>
    <li>circumstance_phrase->with a look of shame</li>
    <li>circumstance_phrase->while others look on</li>
    <li>circumstance_phrase->with gusto</li>
    <li>circumstance_phrase->frantically, like [PAWN_possessive] life depended on it</li>
    <li>desc_sentence->[PAWN_nameDef]'s face is covered with blood and fluid.</li>
    <li>desc_sentence->[PAWN_nameDef] is licking [PAWN_possessive] fingers.</li>
    <li>desc_sentence->[PAWN_nameDef] has blood and gore bits all down [PAWN_possessive] front.</li>
    <li>desc_sentence->[PAWN_nameDef] is in the middle of a large pool of blood.</li>
    <li>desc_sentence->[PAWN_nameDef] is eyeing someone else nearby with dark interest.</li>
    <li>desc_sentence->The meat is glistening and appears very succulent.</li>
    <li>desc_sentence->The meat is spilling all over [PAWN_nameDef]'s body.</li>
  -->
  <AteRawHumanlikeMeat.rulePack.rulesStrings>
    <li>tale_noun->[PAWN_nameDef] їсть м'ясо людини</li>
    <li>image->[PAWN_nameFull] [circumstance_group] [eat_gerund] м'ясо людини</li>
    <li>image->[PAWN_nameFull] [circumstance_group] [eat_gerund] м'ясо людини з руки</li>
    <li>image->[PAWN_nameFull] [circumstance_group] [eat_gerund] плоть людини</li>
    <li>eat_gerund->їсть</li>
    <li>eat_gerund->проковтує</li>
    <li>eat_gerund->жує</li>
    <li>eat_gerund->пережовує</li>
    <li>eat_gerund->споживає</li>
    <li>eat_gerund->ковтає</li>
    <li>eat_gerund->пожирає</li>
    <li>circumstance_phrase->з почуттям мети</li>
    <li>circumstance_phrase->без сорому</li>
    <li>circumstance_phrase->соромлячись</li>
    <li>circumstance_phrase->поки інші дивляться</li>
    <li>circumstance_phrase->із смаком</li>
    <li>circumstance_phrase->шалено, наче [PAWN_possessive] життя залежало від цього</li>
    <li>desc_sentence->Обличчя [PAWN_nameDef] вкрите кров'ю.</li>
    <li>desc_sentence->[PAWN_nameDef] облизує свої пальці.</li>
    <li>desc_sentence->[PAWN_nameDef] має крові на собі спереду.</li>
    <li>desc_sentence->[PAWN_nameDef] знаходиться посеред великої калюжі крові.</li>
    <li>desc_sentence->[PAWN_nameDef] кровожерливо дивиться на когось поруч.</li>
    <li>desc_sentence->М'ясо блищить і виглядає дуже соковитим.</li>
    <li>desc_sentence->Куски м'яса розлітаються по всьому тілу [PAWN_nameDef].</li>
  </AteRawHumanlikeMeat.rulePack.rulesStrings>
  
  <!-- EN: humanlike corpse butchered -->
  <ButcheredHumanlikeCorpse.label>розчленовано людський труп </ButcheredHumanlikeCorpse.label>
  
  <!-- EN: art crafted -->
  <CraftedArt.label>витвір мистецтва</CraftedArt.label>
  <!-- EN:
    <li>tale_noun->the time [PAWN_nameDef] crafted [THING_indefinite]</li>
    <li>image->[PAWN_nameFull] crafting [THING_indefinite] [circumstance_group]. [quality_sentence]. [title_sentence]</li>
    <li>image->[PAWN_nameFull] completing [PAWN_possessive] work on [THING_indefinite] [circumstance_group]. [quality_sentence]. [title_sentence]</li>
    <li>image->[PAWN_nameFull] working on [THING_indefinite] [circumstance_group]. [quality_sentence]. [title_sentence]</li>
    <li>image->[PAWN_nameFull] making [THING_indefinite] [circumstance_group]. [quality_sentence]. [title_sentence]</li>
    <li>circumstance_phrase->with total concentration</li>
    <li>circumstance_phrase->with a look of satisfaction on [PAWN_possessive] face</li>
    <li>circumstance_phrase->at [PAWN_possessive] work bench</li>
    <li>circumstance_phrase->with great intensity</li>
    <li>desc_sentence->There are tools scattered all around.</li>
    <li>desc_sentence->[PAWN_pronoun] is scratched and scarred from work injuries.</li>
    <li>desc_sentence->[PAWN_pronoun] is covered in sweat.</li>
    <li>desc_sentence->The work area is highly organized, with every tool in its proper place.</li>
    <li>desc_sentence->[PAWN_pronoun] is rendered in an exaggerated way to appear more powerful.</li>
    <li>desc_sentence->The size of [THING_definite] is exaggerated to emphasize its importance.</li>
    <li>desc_sentence->[THING_definite] has an artistic glow added to it. It seems almost angelic.</li>
    <li>desc_sentence->[PAWN_nameDef] is faded into the background to emphasize [PAWN_possessive] new creation.</li>
    <li>desc_sentence->[Quantity_adjphrase] onlookers surround [PAWN_objective].</li>
    <li>desc_sentence->A crowd cheers from the background.</li>
    <li>quality_sentence->[THING_definite] looks to be of [THING_quality] quality</li>
    <li>quality_sentence->[THING_definite] is of [THING_quality] quality</li>
    <li>quality_sentence->[PAWN_nameDef]'s work is of [THING_quality] quality</li>
    <li>title_sentence->[PAWN_nameDef]'s title for [THING_definite] is written underneath: [THING_title]</li>
    <li>title_sentence->[THING_definite] is emblazoned with its title: [THING_title]</li>
    <li>title_sentence->The title of [THING_definite], [THING_title], hangs in the background</li>
  -->
  <CraftedArt.rulePack.rulesStrings>
    <li>tale_noun->[PAWN_nameDef] створив [THING_indefinite]</li>
    <li>image->[PAWN_nameFull] виготовляє [THING_indefinite] [circumstance_group]. [quality_sentence]. [title_sentence]</li>
    <li>image->[PAWN_nameFull] закінчує свою працю над [THING_indefinite] [circumstance_group]. [quality_sentence]. [title_sentence]</li>
    <li>image->[PAWN_nameFull] працює над [THING_indefinite] [circumstance_group]. [quality_sentence]. [title_sentence]</li>
    <li>image->[PAWN_nameFull] робить [THING_indefinite] [circumstance_group]. [quality_sentence]. [title_sentence]</li>
    <li>circumstance_phrase->повністю сконцентрувавшись</li>
    <li>circumstance_phrase->з виразом задоволення на своєму обличчі</li>
    <li>circumstance_phrase->на своєму робочому столі</li>
    <li>circumstance_phrase->з великим старанням</li>
    <li>desc_sentence->Деякі інструменти розкидані навколо.</li>
    <li>desc_sentence->[PAWN_pronoun] має подряпини та шрами від робочих ушкоджень.</li>
    <li>desc_sentence->[PAWN_pronoun] у поті.</li>
    <li>desc_sentence->Робочий простір організовано так, що кожен інструмент на своєму місці.</li>
    <li>desc_sentence->[PAWN_pronoun] передається у перебільшений спосіб, щоб виглядати потужнішим.</li>
    <li>desc_sentence->Розмір [THING_definite] перебільшено, щоб підкреслити його важливість.</li>
    <li>desc_sentence->[THING_definite] має мистецьке сяйво. Здається майже ангельським.</li>
    <li>desc_sentence->[PAWN_nameDef] відходить на задній план, щоб підкреслити нове створення [PAWN_possessive].</li>
    <li>desc_sentence->[Quantity_adjphrase] глядачі оточують [PAWN_objective].</li>
    <li>desc_sentence->Натовп вигукує на задньому плані.</li>
    <li>quality_sentence->[THING_definite] виглядає як [THING_quality]</li>
    <li>quality_sentence->[THING_definite] має якість [THING_quality]</li>
    <li>quality_sentence->[PAWN_nameDef] зроблено з якістю [THING_quality]</li>
    <li>title_sentence->[PAWN_nameDef] автор назвав вітвір [THING_definite] написана під: [THING_title]</li>
    <li>title_sentence->[THING_definite] прикрашено назвою: [THING_title]</li>
    <li>title_sentence->Назва [THING_title], висить над [THING_definite]</li>
  </CraftedArt.rulePack.rulesStrings>
  
  <!-- EN: drunk -->
  <Drunk.label>п’яний</Drunk.label>
  <!-- EN:
    <li>tale_noun->[PAWN_nameDef]'s extreme drunkenness</li>
    <li>tale_noun->[PAWN_nameDef] getting extremely drunk</li>
    <li>image->[PAWN_nameFull] staggering around drunk [circumstance_group]</li>
    <li>image->[PAWN_nameFull] tilting [PAWN_possessive] head back and guzzling liquor [circumstance_group]</li>
    <li>image->[PAWN_nameFull] greedily collecting bottles of liquor [circumstance_group]</li>
    <li>image->[PAWN_nameFull] drinking heavily [circumstance_group]</li>
    <li>circumstance_phrase->oblivious to [PAWN_possessive] surroundings</li>
    <li>circumstance_phrase->in a brooding stupor</li>
    <li>circumstance_phrase->while questioning [PAWN_possessive] own existence</li>
    <li>circumstance_phrase->with tears in [PAWN_possessive] eyes</li>
    <li>circumstance_phrase->while chuckling madly</li>
    <li>circumstance_phrase->while sobbing</li>
    <li>circumstance_phrase->while looking pathetic</li>
    <li>circumstance_phrase->while glaring angrily at people around [PAWN_objective]</li>
    <li>circumstance_phrase->while leering at someone nearby</li>
    <li>circumstance_phrase->while attempting to disrobe</li>
    <li>circumstance_phrase->with a finger in [PAWN_possessive] mouth</li>
    <li>circumstance_phrase->while holding back vomit</li>
    <li>circumstance_phrase->without a care in the world</li>
    <li>circumstance_phrase->with a lustful glint in [PAWN_possessive] eye</li>
    <li>circumstance_phrase->while reviewing the ghosts of [PAWN_possessive] past</li>
    <li>desc_sentence->[PAWN_pronoun] seems totally unaware of what is around [PAWN_objective].</li>
    <li>desc_sentence->[PAWN_possessive] face itself seems to be swelling.</li>
    <li>desc_sentence->[PAWN_pronoun] is nearly unconscious, [PAWN_possessive] tongue lolling out, drool dripping.</li>
    <li>desc_sentence->[PAWN_pronoun] looks happy and sad at the same time.</li>
    <li>desc_sentence->[PAWN_pronoun] has stains down [PAWN_possessive] front.</li>
    <li>desc_sentence->There is a trail of discarded beverage containers behind [PAWN_objective].</li>
    <li>desc_sentence->There is a white substance on [PAWN_possessive] pants.</li>
    <li>desc_sentence->[PAWN_pronoun] seems to have lost a shoe.</li>
    <li>desc_sentence->[PAWN_possessive] hair is totally mussed up.</li>
  -->
  <Drunk.rulePack.rulesStrings>
    <li>tale_noun->[PAWN_nameDef] п'яний до смерті</li>
    <li>tale_noun->[PAWN_nameDef] дуже п'яний</li>
    <li>image->[PAWN_nameFull] хитається п'яний [circumstance_group]</li>
    <li>image->[PAWN_nameFull] підіймає [PAWN_possessive] голову щоб влити напій в горлянку [circumstance_group]</li>
    <li>image->[PAWN_nameFull] жадібно збирає пляшки з алкоголем [circumstance_group]</li>
    <li>image->[PAWN_nameFull] важко п'є [circumstance_group]</li>
    <li>circumstance_phrase->не звертає уваги на оточення [PAWN_possessive]</li>
    <li>circumstance_phrase->в задумливому ступорі</li>
    <li>circumstance_phrase->ставлячи під сумнів власне існування [PAWN_possessive]</li>
    <li>circumstance_phrase->зі слізьми в [PAWN_possessive] очах</li>
    <li>circumstance_phrase->шалено посміхаючись</li>
    <li>circumstance_phrase->ридаючи</li>
    <li>circumstance_phrase->виглядає патетично</li>
    <li>circumstance_phrase->сердито дивиться на людей навколо [PAWN_objective]</li>
    <li>circumstance_phrase->дивиться на когось поруч</li>
    <li>circumstance_phrase->робить спроби роздягнутися</li>
    <li>circumstance_phrase->з пальцем у [PAWN_possessive] роті</li>
    <li>circumstance_phrase->стримуючи блювоту</li>
    <li>circumstance_phrase->без турботи про світ</li>
    <li>circumstance_phrase->з хтивим блиском в очах [PAWN_possessive]</li>
    <li>circumstance_phrase->роздумуючи про події минулого [PAWN_possessive]</li>
    <li>desc_sentence->[PAWN_pronoun] здається, абсолютно не знає, що навколо [PAWN_objective].</li>
    <li>desc_sentence->[PAWN_possessive] обличчя ніби набрякло.</li>
    <li>desc_sentence->[PAWN_pronoun] майже без свідомості, [PAWN_possessive] язик висунуся, слина тече.</li>
    <li>desc_sentence->[PAWN_pronoun] виглядає щасливим і сумним водночас.</li>
    <li>desc_sentence->[PAWN_pronoun] має спереду плями [PAWN_possessive].</li>
    <li>desc_sentence->За [PAWN_objective] є сліди від викинутих емностей для напоїв.</li>
    <li>desc_sentence->На штанах [PAWN_possessive] видно білу речовину.</li>
    <li>desc_sentence->[PAWN_pronoun] схоже загубив черевик.</li>
    <li>desc_sentence->[PAWN_possessive] волосся повністю скуйовджене.</li>
  </Drunk.rulePack.rulesStrings>
  
  <!-- EN: research project finished -->
  <FinishedResearchProject.label>проект дослідження завершено</FinishedResearchProject.label>
  <!-- EN:
    <li>tale_noun->[PAWN_nameDef] finishing research on [PROJECT_label]</li>
    <li>image->[PAWN_nameFull] working on the [PROJECT_label] research project [circumstance_group]</li>
    <li>image->[PAWN_nameFull] studying the secrets of [PROJECT_label] [circumstance_group]</li>
    <li>image->[PAWN_nameFull] researching [PROJECT_label] [circumstance_group]</li>
    <li>circumstance_phrase->with great intensity</li>
    <li>circumstance_phrase->alone at [PAWN_possessive] bench</li>
    <li>circumstance_phrase->while holding papers in [PAWN_possessive] hand</li>
    <li>circumstance_phrase->with a look of gleeful fascination</li>
    <li>desc_sentence->[PAWN_nameDef] is sweating.</li>
    <li>desc_sentence->The work appears to be exceptionally complex.</li>
    <li>desc_sentence->[PAWN_nameDef] is completely surrounded by an array of tools and apparatuses.</li>
    <li>desc_sentence->[PAWN_nameDef] is staring at [PAWN_possessive] discovery with a sense of wonder.</li>
  -->
  <FinishedResearchProject.rulePack.rulesStrings>
    <li>tale_noun->[PAWN_nameDef] завершено дослідження [PROJECT_label]</li>
    <li>image->[PAWN_nameFull] працює над [PROJECT_label] достідницьким проєктом [circumstance_group]</li>
    <li>image->[PAWN_nameFull] вивчає секрети [PROJECT_label] [circumstance_group]</li>
    <li>image->[PAWN_nameFull] досліджує [PROJECT_label] [circumstance_group]</li>
    <li>circumstance_phrase->з великим старанням</li>
    <li>circumstance_phrase->сам на лавці [PAWN_possessive]</li>
    <li>circumstance_phrase->тримаючи папери в руці [PAWN_possessive]</li>
    <li>circumstance_phrase->з радісним поглядом очікування</li>
    <li>desc_sentence->[PAWN_nameDef] пітніє.</li>
    <li>desc_sentence->Робота, як видається, є надзвичайно складною.</li>
    <li>desc_sentence->[PAWN_nameDef] в оточені безлічі інструментів і приладів.</li>
    <li>desc_sentence->[PAWN_nameDef] дивиться на відкриття [PAWN_possessive] із почуттям подиву.</li>
  </FinishedResearchProject.rulePack.rulesStrings>
  
  <!-- EN: landed in pod -->
  <LandedInPod.label>сісти у капсулу</LandedInPod.label>
  <!-- EN:
    <li>tale_noun->[PAWN_nameDef]'s landing in a drop pod</li>
    <li>image->[PAWN_nameFull] landing in a drop pod [circumstance_group]</li>
    <li>image->[PAWN_nameFull] touching down in a drop pod [circumstance_group]</li>
    <li>image->[PAWN_nameFull] striking earth in a drop pod [circumstance_group]</li>
    <li>image->[PAWN_nameFull] riding in a drop pod [circumstance_group]</li>
    <li>circumstance_phrase->in front of a [TerrainFeature]</li>
    <li>circumstance_phrase->with incredible force</li>
    <li>circumstance_phrase->in a plume of dust and rocks</li>
    <li>circumstance_phrase->with retro-rockets firing dramatically</li>
    <li>circumstance_phrase->in a precision landing</li>
    <li>desc_sentence->[PAWN_pronoun] is concentrating intently on the controls.</li>
    <li>desc_sentence->[PAWN_pronoun] has [PAWN_possessive] eyes closed and looks afraid.</li>
    <li>desc_sentence->[PAWN_pronoun] is unconscious, [PAWN_possessive] tongue lolling out, drool dripping.</li>
    <li>desc_sentence->[PAWN_pronoun] is smiling with grim joy.</li>
    <li>desc_sentence->[PAWN_pronoun] seems to have no idea what [PAWN_pronoun] is doing.</li>
    <li>desc_sentence->[PAWN_pronoun] is strapped in with [PAWN_possessive] eyes closed, totally helpless.</li>
    <li>desc_sentence->There is a flame trail licking off the back of the pod.</li>
    <li>desc_sentence->A nearby [Animal] is looking up, startled.</li>
    <li>desc_sentence->A [Animal] is fleeing the impact in fear.</li>
    <li>desc_sentence->There is a [TerrainFeature] in the background.</li>
    <li>desc_sentence->A [PersonJob] watches silently from afar.</li>
  -->
  <LandedInPod.rulePack.rulesStrings>
    <li>tale_noun->[PAWN_nameDef] сідає до скидувальної капсули</li>
    <li>image->[PAWN_nameFull] сідає до скидувальної капсули [circumstance_group]</li>
    <li>image->[PAWN_nameFull] торкається скидувальної капсули [circumstance_group]</li>
    <li>image->[PAWN_nameFull] врізається у землю в скидувальній капсулі [circumstance_group]</li>
    <li>image->[PAWN_nameFull] рухаеться в скидувальній капсулі [circumstance_group]</li>
    <li>circumstance_phrase->з переду [TerrainFeature]</li>
    <li>circumstance_phrase->з неймовірною силою</li>
    <li>circumstance_phrase->в хмарах пилі та каміння</li>
    <li>circumstance_phrase->з працюючими ракето-двигунами</li>
    <li>circumstance_phrase->в точному приземлені</li>
    <li>desc_sentence->[PAWN_pronoun] зосереджий на елементах керування.</li>
    <li>desc_sentence->[PAWN_pronoun] із [PAWN_possessive] закритими очима та виглядає наляканим.</li>
    <li>desc_sentence->[PAWN_pronoun] непритомний, [PAWN_possessive] язик висуното, слина тече.</li>
    <li>desc_sentence->[PAWN_pronoun] зловісно посміхається.</li>
    <li>desc_sentence->[PAWN_pronoun], здається, не має жодного уявлення, що він робить [PAWN_pronoun].</li>
    <li>desc_sentence->[PAWN_pronoun] прив’язаний із закритими очима [PAWN_possessive], абсолютно безпорадний.</li>
    <li>desc_sentence->На задній частині капсули видно слід полум’я.</li>
    <li>desc_sentence-> [Animal] злякано споглядає догори.</li>
    <li>desc_sentence->[Animal] у страху тікає від удару.</li>
    <li>desc_sentence->[TerrainFeature] видно недалеко.</li>
    <li>desc_sentence->[PersonJob] мовчки дивиться іздалека.</li>
  </LandedInPod.rulePack.rulesStrings>
  
  <!-- EN: berserk rage -->
  <MentalStateBerserk.label>несамовита лють</MentalStateBerserk.label>
  <!-- EN:
    <li>tale_noun->[PAWN_nameDef] going berserk</li>
    <li>image->[PAWN_nameFull] flying into a berserk rage [circumstance_group]</li>
    <li>image->[PAWN_nameFull] becoming madly, violently insane [circumstance_group]</li>
    <li>image->[PAWN_nameFull] stumbling forward with a psychotic look on [PAWN_possessive] face [circumstance_group]</li>
    <li>circumstance_phrase->while attempting to disrobe</li>
    <li>circumstance_phrase->seemingly without reason</li>
    <li>circumstance_phrase->as others cower in fear</li>
    <li>circumstance_phrase->as a friend flees</li>
    <li>circumstance_phrase->because of the stress</li>
    <li>circumstance_phrase->as a last step</li>
    <li>desc_sentence->[PAWN_pronoun] is shaking with ungovernable rage.</li>
    <li>desc_sentence->[PAWN_possessive] teeth are bared in a deadly snarl.</li>
    <li>desc_sentence->[PAWN_possessive] eyes are dead pools of madness.</li>
    <li>desc_sentence->Spittle is flying from [PAWN_possessive] mouth as [PAWN_possessive] screams with insane rage.</li>
    <li>desc_sentence->[PAWN_pronoun] has lost part of [PAWN_possessive] clothing.</li>
    <li>desc_sentence->[PAWN_pronoun] is grimacing in misery.</li>
    <li>desc_sentence->[PAWN_pronoun] seems smiling maniacally.</li>
    <li>desc_sentence->[PAWN_pronoun] is depicted with the snarling face of a [Animal].</li>
    <li>desc_sentence->[Animal]s symbolically surround [PAWN_possessive] head.</li>
    <li>desc_sentence->[PAWN_pronoun] has a murderous glint in [PAWN_possessive] eye.</li>
    <li>desc_sentence->[PAWN_possessive] entire body seems to be trembling with hatred.</li>
    <li>desc_sentence->[PAWN_possessive] face is set in a look of twisted serenity.</li>
    <li>desc_sentence->A single tear rolls down [PAWN_possessive] face.</li>
  -->
  <MentalStateBerserk.rulePack.rulesStrings>
    <li>tale_noun->[PAWN_nameDef] стає берсеркером</li>
    <li>image->[PAWN_nameFull] впадає в шалений гнів [circumstance_group]</li>
    <li>image->[PAWN_nameFull] стає божевільним, жорстоко божевільним [circumstance_group]</li>
    <li>image->[PAWN_nameFull] іде вперед із застиглимвиглядом на обличчі [PAWN_possessive] [circumstance_group]</li>
    <li>circumstance_phrase->робить спроби роздягнутися</li>
    <li>circumstance_phrase->начебто без причини</li>
    <li>circumstance_phrase->тоді як інші здригаються від страху</li>
    <li>circumstance_phrase->як друг тікає</li>
    <li>circumstance_phrase->через стрес</li>
    <li>circumstance_phrase->як останній крок</li>
    <li>desc_sentence->[PAWN_pronoun] тремтить від нестримної люті.</li>
    <li>desc_sentence->[PAWN_possessive] шкірить зуби в смертельному гарчанні.</li>
    <li>desc_sentence->[PAWN_possessive] очі - це мертві водойми божевілля.</li>
    <li>desc_sentence->З рота [PAWN_possessive] летять слюні, та [PAWN_possessive] кричить від божевільної люті.</li>
    <li>desc_sentence->[PAWN_pronoun] останні частини одягу [PAWN_possessive].</li>
    <li>desc_sentence->[PAWN_pronoun] кривиться в нещасті.</li>
    <li>desc_sentence->[PAWN_pronoun] маніакально посміхається.</li>
    <li>desc_sentence->[PAWN_pronoun] виглядає з гарчачим обличчям як [Animal].</li>
    <li>desc_sentence->[Animal] символічно оточують голову [PAWN_possessive].</li>
    <li>desc_sentence->[PAWN_pronoun] має вбивчий блиск в очах [PAWN_possessive].</li>
    <li>desc_sentence->[PAWN_possessive] здається, усе тіло тремтить від ненависті.</li>
    <li>desc_sentence->[PAWN_possessive] обличчя має спотворений спокій.</li>
    <li>desc_sentence->Одна сльоза скочується по обличчю [PAWN_possessive].</li>
  </MentalStateBerserk.rulePack.rulesStrings>
  
  <!-- EN: gave up -->
  <MentalStateGaveUp.label>здався</MentalStateGaveUp.label>
  <!-- EN:
    <li>tale_noun->[PAWN_nameDef] giving up in despair</li>
    <li>image->[PAWN_nameFull] finally giving up under stress [circumstance_group]</li>
    <li>image->[PAWN_nameFull] sobbing uncontrollably [circumstance_group]</li>
    <li>image->[PAWN_nameFull] stumbling around with a completely broken expression on [PAWN_possessive] face [circumstance_group]</li>
    <li>circumstance_phrase->while attempting to disrobe</li>
    <li>circumstance_phrase->seemingly without reason</li>
    <li>circumstance_phrase->as others offer sympathy</li>
    <li>circumstance_phrase->as a friend cries</li>
    <li>circumstance_phrase->because of the stress</li>
    <li>circumstance_phrase->as a last step</li>
    <li>desc_sentence->[PAWN_pronoun] has tears streaming down [PAWN_possessive] face.</li>
    <li>desc_sentence->[PAWN_pronoun] is laughing in the depths of [PAWN_possessive] depression.</li>
    <li>desc_sentence->[PAWN_nameDef] is looking upward, as if to ask for help from above.</li>
    <li>desc_sentence->[PAWN_pronoun] is tearing at [PAWN_possessive] own clothes.</li>
    <li>desc_sentence->[PAWN_pronoun] seems totally unaware of what is around [PAWN_objective].</li>
    <li>desc_sentence->[PAWN_pronoun] looks happy and sad at the same time.</li>
    <li>desc_sentence->[PAWN_pronoun] has stains down [PAWN_possessive] front.</li>
    <li>desc_sentence->[PAWN_pronoun] seems to have lost a shoe.</li>
    <li>desc_sentence->[PAWN_possessive] hair is totally mussed up.</li>
  -->
  <MentalStateGaveUp.rulePack.rulesStrings>
    <li>tale_noun->[PAWN_nameDef] здаючись у розпачі</li>
    <li>image->[PAWN_nameFull] нарешті здався під час стресу [circumstance_group]</li>
    <li>image->[PAWN_nameFull] нестримно ридає [circumstance_group]</li>
    <li>image->[PAWN_nameFull] спотикаючись із повністю розгубленим виразом обличчя [PAWN_possessive] [circumstance_group]</li>
    <li>circumstance_phrase->робить спроби роздягнутися</li>
    <li>circumstance_phrase->начебто без причини</li>
    <li>circumstance_phrase->як інші висловлюють співчуття</li>
    <li>circumstance_phrase->як друг плаче</li>
    <li>circumstance_phrase->через стрес</li>
    <li>circumstance_phrase->як останній крок</li>
    <li>desc_sentence->[PAWN_pronoun] по обличчю [PAWN_possessive] течуть сльози.</li>
    <li>desc_sentence->[PAWN_pronoun] сміється в глибокій [PAWN_possessive] депресії.</li>
    <li>desc_sentence->[PAWN_nameDef] дивиться вгору, ніби просить допомоги з небес.</li>
    <li>desc_sentence->[PAWN_pronoun] рве [PAWN_possessive] власний одяг.</li>
    <li>desc_sentence->[PAWN_pronoun] здається, абсолютно не знає, що навколо [PAWN_objective].</li>
    <li>desc_sentence->[PAWN_pronoun] виглядає щасливим і сумним водночас.</li>
    <li>desc_sentence->[PAWN_pronoun] має спереду плями [PAWN_possessive].</li>
    <li>desc_sentence->[PAWN_pronoun] схоже загубив черевик.</li>
    <li>desc_sentence->[PAWN_possessive] волосся повністю скуйовджене.</li>
  </MentalStateGaveUp.rulePack.rulesStrings>
  
  <!-- EN: struck mineable -->
  <StruckMineable.label>гірництво</StruckMineable.label>
  <!-- EN:
    <li>tale_noun->[PAWN_nameDef] striking [THING_label]</li>
    <li>image->[PAWN_nameFull] striking [THING_label] [circumstance_group]</li>
    <li>circumstance_phrase->while mining</li>
    <li>circumstance_phrase->while digging</li>
    <li>circumstance_phrase->while tunnelling</li>
    <li>circumstance_phrase->with a look of surprise</li>
    <li>circumstance_phrase->with a satisfied expression</li>
    <li>desc_sentence->[PAWN_nameDef] is wiping [PAWN_possessive] brow.</li>
    <li>desc_sentence->[PAWN_nameDef] is jumping for joy.</li>
    <li>desc_sentence->[PAWN_nameDef] is high-fiving a friend.</li>
    <li>desc_sentence->[PAWN_nameDef] is screaming with happiness.</li>
    <li>desc_sentence->[PAWN_nameDef] is laughing uncontrollably.</li>
    <li>desc_sentence->[PAWN_nameDef] is sweaty and dirty from work.</li>
    <li>desc_sentence->[PAWN_nameDef] is sweaty and dirty from work.</li>
  -->
  <StruckMineable.rulePack.rulesStrings>
    <li>tale_noun->[PAWN_nameDef] попадає по [THING_label]</li>
    <li>image->[PAWN_nameFull] вдаряє по [THING_label] [circumstance_group]</li>
    <li>circumstance_phrase->добуваючи</li>
    <li>circumstance_phrase->копає</li>
    <li>circumstance_phrase->прокладає тунель</li>
    <li>circumstance_phrase->виглядає сюрприз</li>
    <li>circumstance_phrase->із задоволеним виразом обличчя</li>
    <li>desc_sentence->[PAWN_nameDef] витирається чоло [PAWN_possessive].</li>
    <li>desc_sentence->[PAWN_nameDef] стрибає від радості.</li>
    <li>desc_sentence->[PAWN_nameDef] дає п'ять другу.</li>
    <li>desc_sentence->[PAWN_nameDef] кричить від щастя.</li>
    <li>desc_sentence->[PAWN_nameDef] нестримно сміється.</li>
    <li>desc_sentence->[PAWN_nameDef] спітнілий та брудний від праці.</li>
    <li>desc_sentence->[PAWN_nameDef] втомлений та брудний від праці.</li>
  </StruckMineable.rulePack.rulesStrings>
  
  <!-- EN: vomited -->
  <Vomited.label>блювати</Vomited.label>
  <!-- EN:
    <li>tale_noun->[PAWN_nameDef]'s vomiting</li>
    <li>image->[PAWN_nameFull] spewing vomit onto the ground [circumstance_group]</li>
    <li>image->[PAWN_nameFull] looking disgusted while covered with dried vomit [circumstance_group]</li>
    <li>image->[PAWN_nameFull] doubled over and retching onto the floor [circumstance_group]</li>
    <li>image->[PAWN_nameFull] on [PAWN_possessive] knees, vomiting on the floor [circumstance_group]</li>
    <li>circumstance_phrase->while looking pained</li>
    <li>circumstance_phrase->with great shame</li>
    <li>circumstance_phrase->as others look on</li>
    <li>desc_sentence->[PAWN_pronoun] seems totally unaware of what is around [PAWN_objective].</li>
    <li>desc_sentence->[PAWN_possessive] face itself seems to be swelling.</li>
    <li>desc_sentence->[PAWN_pronoun] is nearly unconscious, [PAWN_possessive] tongue lolling out, drool dripping.</li>
    <li>desc_sentence->[PAWN_pronoun] is convulsing violently.</li>
    <li>desc_sentence->[PAWN_pronoun] looks ashamed.</li>
    <li>desc_sentence->[PAWN_pronoun] seems to be trying to laugh, despite the circumstances.</li>
    <li>desc_sentence->[PAWN_pronoun] looks almost deflated, as though totally emptied by the intense vomiting.</li>
    <li>desc_sentence->[PAWN_pronoun] is surrounded by an artistically rendered halo of filth.</li>
    <li>desc_sentence->A [Animal] is eating from the trail of vomit in the background.</li>
  -->
  <Vomited.rulePack.rulesStrings>
    <li>tale_noun->[PAWN_nameDef] блює</li>
    <li>image->[PAWN_nameFull] склоняєтся блюючи на землю [circumstance_group]</li>
    <li>image->[PAWN_nameFull] виглядати огидно, коли він покритий засохлою блювотою [circumstance_group]</li>
    <li>image->[PAWN_nameFull] блював та підковзнувся, впав на підлогу [circumstance_group]</li>
    <li>image->[PAWN_nameFull] [PAWN_possessive] на колінах, бдюєть на підлозі [circumstance_group]</li>
    <li>circumstance_phrase->боляче дивитись</li>
    <li>circumstance_phrase->з великим соромом</li>
    <li>circumstance_phrase->як інші дивляться на</li>
    <li>desc_sentence->[PAWN_pronoun] здається, абсолютно не знає, що навколо [PAWN_objective].</li>
    <li>desc_sentence->[PAWN_possessive] обличчя ніби набрякло.</li>
    <li>desc_sentence->[PAWN_pronoun] майже без свідомості, [PAWN_possessive] язик висунуся, слина тече.</li>
    <li>desc_sentence->[PAWN_pronoun] сильно судомиться.</li>
    <li>desc_sentence->[PAWN_pronoun] виглядає соромно.</li>
    <li>desc_sentence->[PAWN_pronoun] намагається сміятися, незважаючи на обставини.</li>
    <li>desc_sentence->[PAWN_pronoun] виглядає майже спустошеним, через інтенсивну блювоту.</li>
    <li>desc_sentence->[PAWN_pronoun] оточений художньо переданим ореолом бруду.</li>
    <li>desc_sentence->[Animal] їсть зі сліду блювоти позаду.</li>
  </Vomited.rulePack.rulesStrings>
  
  <!-- EN: walked naked -->
  <WalkedNaked.label>ходити голим</WalkedNaked.label>
  <!-- EN:
    <li>tale_noun->[PAWN_nameDef] walking around naked</li>
    <li>image->[PAWN_nameFull] [nude_action] while in a state of nature [circumstance_group]</li>
    <li>image->[PAWN_nameFull] [nude_action] in the nude [circumstance_group]</li>
    <li>image->[PAWN_nameFull] [nude_action], naked, [circumstance_group]</li>
    <li>image->[PAWN_nameFull] [nude_action] without any clothes on [circumstance_group]</li>
    <li>nude_action->prancing</li>
    <li>nude_action->frolicking</li>
    <li>nude_action->gambolling</li>
    <li>nude_action->walking</li>
    <li>nude_action->strutting [PAWN_possessive] stuff</li>
    <li>nude_action->sashaying</li>
    <li>nude_action->tiptoeing</li>
    <li>nude_action->promenading</li>
    <li>nude_action->surveying the area</li>
    <li>circumstance_phrase->with a sense of purpose</li>
    <li>circumstance_phrase->with no hint of shame</li>
    <li>circumstance_phrase->while others look on</li>
    <li>circumstance_phrase->for no apparent reason</li>
    <li>circumstance_phrase->while confused animals look on</li>
    <li>desc_sentence->[PAWN_nameDef] is visibly aroused.</li>
    <li>desc_sentence->[PAWN_nameDef] is covered in unexplained moisture.</li>
    <li>desc_sentence->[PAWN_nameDef] is breathing heavily for no obvious reason.</li>
    <li>desc_sentence->[PAWN_nameDef] is fondling a shrub.</li>
  -->
  <WalkedNaked.rulePack.rulesStrings>
    <li>tale_noun->[PAWN_nameDef] ходити голим</li>
    <li>image->[PAWN_nameFull] [nude_action] близький до природи [circumstance_group]</li>
    <li>image->[PAWN_nameFull] [nude_action] {0_gender ? оголений : оголена}[circumstance_group]</li>
    <li>image->[PAWN_nameFull] [nude_action], нагий, [circumstance_group]</li>
    <li>image->[PAWN_nameFull] [nude_action] без будьякого одягу [circumstance_group]</li>
    <li>nude_action->підстрибуючи</li>
    <li>nude_action->пустуючий</li>
    <li>nude_action->азартний</li>
    <li>nude_action->гуляючий</li>
    <li>nude_action->пихатий [PAWN_possessive] речі</li>
    <li>nude_action->виступає</li>
    <li>nude_action->іде навшпиньки</li>
    <li>nude_action->прогулюеться</li>
    <li>nude_action->оглядає місцевість</li>
    <li>circumstance_phrase->з почуттям мети</li>
    <li>circumstance_phrase->без сорому</li>
    <li>circumstance_phrase->поки інші дивляться</li>
    <li>circumstance_phrase->без видимої причини</li>
    <li>circumstance_phrase->а збентежені тварини дивляться</li>
    <li>desc_sentence->[PAWN_nameDef] помітно збуджений.</li>
    <li>desc_sentence->[PAWN_nameDef] вкривається незрозумілою вологою.</li>
    <li>desc_sentence->[PAWN_nameDef] важко дихає без видимих причин.</li>
    <li>desc_sentence->[PAWN_nameDef] пестить кущ.</li>
  </WalkedNaked.rulePack.rulesStrings>
  
  <!-- EN: on fire -->
  <WasOnFire.label>у полум'ї</WasOnFire.label>
  <!-- EN:
    <li>tale_noun->[PAWN_nameDef] catching fire</li>
    <li>image->[PAWN_nameFull] frantically beating out a fire attached to [PAWN_possessive] body [circumstance_group]</li>
    <li>image->[PAWN_nameFull] enveloped by flame [circumstance_group]</li>
    <li>image->[PAWN_nameFull] kneeling, hands over head, trying to extinguish flames on [PAWN_possessive] body [circumstance_group]</li>
    <li>image->[PAWN_nameFull] rolling on the floor while burning [circumstance_group]</li>
    <li>circumstance_phrase->while others look on</li>
    <li>circumstance_phrase->while nearly naked</li>
    <li>circumstance_phrase->with focused intent</li>
    <li>desc_sentence->[PAWN_possessive] flesh is visibly charring.</li>
    <li>desc_sentence->[PAWN_possessive] eyes are wide with panic.</li>
    <li>desc_sentence->[PAWN_pronoun] seems to be barely conscious; [PAWN_possessive] eyes are lifeless.</li>
    <li>desc_sentence->[PAWN_possessive] mouth is open as [PAWN_pronoun] screams for help.</li>
    <li>desc_sentence->The flames are about to envelope [PAWN_possessive] head.</li>
    <li>desc_sentence->A symbolic halo of fire surrounds [PAWN_possessive] face.</li>
    <li>desc_sentence->[PAWN_pronoun] is laughing maniacally.</li>
    <li>desc_sentence->[PAWN_pronoun] seems to be losing [PAWN_objective]self.</li>
    <li>desc_sentence->A plume of smoke is rising off [PAWN_objective].</li>
    <li>desc_sentence->[PAWN_pronoun] is rendered artistically in a corpse-like way.</li>
  -->
  <WasOnFire.rulePack.rulesStrings>
    <li>tale_noun->[PAWN_nameDef] спалахнув</li>
    <li>image->[PAWN_nameFull] несамовито гасити вогонь на тілі [PAWN_possessive] [circumstance_group]</li>
    <li>image->[PAWN_nameFull] охоплений полум'ям [circumstance_group]</li>
    <li>image->[PAWN_nameFull] стоячи на колінах, руки над головою, намагаеться загасити полум’я на тілі [PAWN_possessive] [circumstance_group]</li>
    <li>image->[PAWN_nameFull] катаеться по підлозі під час горіння [circumstance_group]</li>
    <li>circumstance_phrase->поки інші дивляться</li>
    <li>circumstance_phrase->поки майже голий</li>
    <li>circumstance_phrase->з цілеспрямованим наміром</li>
    <li>desc_sentence->[PAWN_possessive] м'якоть помітно обвуглюється.</li>
    <li>desc_sentence->[PAWN_possessive] очи широко відкриті від паніки.</li>
    <li>desc_sentence->[PAWN_pronoun] здається, що ледве притомний; [PAWN_possessive] очі неживі.</li>
    <li>desc_sentence->[PAWN_possessive] рот відкритий, коли [PAWN_pronoun] кричить, кличе допомогу.</li>
    <li>desc_sentence->Полум’я ось-ось огорне голову [PAWN_possessive].</li>
    <li>desc_sentence->Символічний ореол вогню оточує обличчя [PAWN_possessive].</li>
    <li>desc_sentence->[PAWN_pronoun] маніакально сміється.</li>
    <li>desc_sentence->[PAWN_pronoun] здається, втрачає себе [PAWN_objective].</li>
    <li>desc_sentence->Стовп диму піднімається над [PAWN_objective].</li>
    <li>desc_sentence->[PAWN_pronoun] художньо передає трупоподібний вигляд.</li>
  </WasOnFire.rulePack.rulesStrings>
  
</LanguageData>
