<?xml version="1.0" encoding="utf-8"?>
<LanguageData>

  <PrisonCell.stages.0.label>жахлива тюремна камера</PrisonCell.stages.0.label>
  <PrisonCell.stages.0.description>Моя тюремна камера це жахливе місце.</PrisonCell.stages.0.description>
  <PrisonCell.stages.3.label>decent prison cell</PrisonCell.stages.3.label>
  <PrisonCell.stages.3.description>My prison cell is pretty decent.</PrisonCell.stages.3.description>
  <PrisonCell.stages.4.label>slightly impressive prison cell</PrisonCell.stages.4.label>
  <PrisonCell.stages.4.description>My prison cell seems to be a nice place.</PrisonCell.stages.4.description>
  <PrisonCell.stages.5.label>impressive prison cell</PrisonCell.stages.5.label>
  <PrisonCell.stages.5.description>My prison cell is impressive. I can't believe they are keeping me in a room like this.</PrisonCell.stages.5.description>
  <PrisonCell.stages.6.label>very impressive prison cell</PrisonCell.stages.6.label>
  <PrisonCell.stages.6.description>My prison cell is very impressive. I can't believe they are keeping me in a room like this. I love it!</PrisonCell.stages.6.description>
  <PrisonCell.stages.7.label>extremely impressive prison cell</PrisonCell.stages.7.label>
  <PrisonCell.stages.7.description>My prison cell is extremely impressive. I can't believe they are keeping me in a room like this. I love it!</PrisonCell.stages.7.description>
  <PrisonCell.stages.8.label>unbelievably impressive prison cell</PrisonCell.stages.8.label>
  <PrisonCell.stages.8.description>My prison cell is unbelievably impressive. This is the best place ever!</PrisonCell.stages.8.description>
  <PrisonCell.stages.9.label>wondrously impressive prison cell</PrisonCell.stages.9.label>
  <PrisonCell.stages.9.description>My prison cell is the best place one can ever imagine. I can stay here forever.</PrisonCell.stages.9.description>

  <PrisonBarracks.stages.0.label>жахлива казарма</PrisonBarracks.stages.0.label>
  <PrisonBarracks.stages.0.description>Моя казарма це жахливе місце.</PrisonBarracks.stages.0.description>
  <PrisonBarracks.stages.1.label>dull barrack</PrisonBarracks.stages.1.label>
  <PrisonBarracks.stages.1.description>I'm living in a dull barrack.</PrisonBarracks.stages.1.description>
  <PrisonBarracks.stages.4.label>slightly impressive barrack</PrisonBarracks.stages.4.label>
  <PrisonBarracks.stages.4.description>My prison barrack is slightly impressive.</PrisonBarracks.stages.4.description>
  <PrisonBarracks.stages.5.label>somewhat impressive barrack</PrisonBarracks.stages.5.label>
  <PrisonBarracks.stages.5.description>My prison barrack is impressive. I like it.</PrisonBarracks.stages.5.description>
  <PrisonBarracks.stages.6.label>very impressive barrack</PrisonBarracks.stages.6.label>
  <PrisonBarracks.stages.6.description>My prison barrack is very impressive. I like it.</PrisonBarracks.stages.6.description>
  <PrisonBarracks.stages.7.label>extremely impressive barrack</PrisonBarracks.stages.7.label>
  <PrisonBarracks.stages.7.description>My prison barrack is extremely impressive. I can't believe they are keeping me in a place like this.</PrisonBarracks.stages.7.description>
  <PrisonBarracks.stages.8.label>unbelievably impressive barrack</PrisonBarracks.stages.8.label>
  <PrisonBarracks.stages.8.description>My prison barrack is unbelievably impressive. I can't believe they are keeping me in a place like this.</PrisonBarracks.stages.8.description>
  <PrisonBarracks.stages.9.label>wondrously impressive barrack</PrisonBarracks.stages.9.label>
  <PrisonBarracks.stages.9.description>My prison barrack is wonderful! I can't believe they are keeping me in a place like this.</PrisonBarracks.stages.9.description>

  <HospitalPatientRoomStats.stages.0.label>жахлива лікарня</HospitalPatientRoomStats.stages.0.label>
  <HospitalPatientRoomStats.stages.0.description>Ця лікарня жахлива.</HospitalPatientRoomStats.stages.0.description>
  <HospitalPatientRoomStats.stages.1.label>dull hospital</HospitalPatientRoomStats.stages.1.label>
  <HospitalPatientRoomStats.stages.1.description>I'm stuck in a dull hospital.</HospitalPatientRoomStats.stages.1.description>
  <HospitalPatientRoomStats.stages.4.label>slightly impressive hospital</HospitalPatientRoomStats.stages.4.label>
  <HospitalPatientRoomStats.stages.4.description>My hospital is slightly impressive. It makes me feel a bit better.</HospitalPatientRoomStats.stages.4.description>
  <HospitalPatientRoomStats.stages.5.label>somewhat impressive hospital</HospitalPatientRoomStats.stages.5.label>
  <HospitalPatientRoomStats.stages.5.description>My hospital is impressive. It makes me feel better.</HospitalPatientRoomStats.stages.5.description>
  <HospitalPatientRoomStats.stages.6.label>very impressive hospital</HospitalPatientRoomStats.stages.6.label>
  <HospitalPatientRoomStats.stages.6.description>My hospital is very impressive. It makes me feel better.</HospitalPatientRoomStats.stages.6.description>
  <HospitalPatientRoomStats.stages.7.label>extremely impressive hospital</HospitalPatientRoomStats.stages.7.label>
  <HospitalPatientRoomStats.stages.7.description>My hospital is extremely impressive. It makes me feel better already.</HospitalPatientRoomStats.stages.7.description>
  <HospitalPatientRoomStats.stages.8.label>unbelievably impressive hospital</HospitalPatientRoomStats.stages.8.label>
  <HospitalPatientRoomStats.stages.8.description>My hospital is unbelievably impressive. It makes me feel better already.</HospitalPatientRoomStats.stages.8.description>
  <HospitalPatientRoomStats.stages.9.label>wondrously impressive hospital</HospitalPatientRoomStats.stages.9.label>
  <HospitalPatientRoomStats.stages.9.description>My hospital is wonderful! It makes me feel better already.</HospitalPatientRoomStats.stages.9.description>


</LanguageData>
